mcp_pypi/__init__.py
mcp_pypi/__main__.py
mcp_pypi/client.py
mcp_pypi/cli/__init__.py
mcp_pypi/cli/main.py
mcp_pypi/cli/server.py
mcp_pypi/cli/server_command.py
mcp_pypi/core/__init__.py
mcp_pypi/core/stats.py
mcp_pypi/core/cache/__init__.py
mcp_pypi/core/http/__init__.py
mcp_pypi/core/models/__init__.py
mcp_pypi/server/__init__.py
mcp_pypi/utils/__init__.py
mcp_pypi/utils/cache.py
mcp_pypi/utils/helpers.py
mcp_pypi/utils/common/__init__.py
mcp_pypi/utils/common/caching.py
mcp_pypi/utils/common/constants.py
mcp_pypi/utils/common/error_handling.py
mcp_pypi/utils/common/validation.py
mcp_pypi-2.7.1.dist-info/licenses/LICENSE
mcp_pypi-2.7.1.dist-info/METADATA
mcp_pypi-2.7.1.dist-info/WHEEL
mcp_pypi-2.7.1.dist-info/entry_points.txt
mcp_pypi-2.7.1.dist-info/top_level.txt
mcp_pypi-2.7.1.dist-info/RECORD
