Metadata-Version: 2.4
Name: mcp-pypi
Version: 2.7.1
Summary: 🐍 AI-powered Python package intelligence - search, analyze, and understand PyPI packages through MCP
Author: Kim Asplund
Author-email: Kim Asplund <kim.asplund@gmail.com>
License: MIT OR Commercial
Project-URL: Homepage, https://github.com/kimasplund/mcp-pypi
Project-URL: Bug Tracker, https://github.com/kimasplund/mcp-pypi/issues
Project-URL: Documentation, https://github.com/kimasplund/mcp-pypi#readme
Project-URL: Source Code, https://github.com/kimasplund/mcp-pypi
Project-URL: Changelog, https://github.com/kimasplund/mcp-pypi/releases
Keywords: mcp,model-context-protocol,pypi,python-packages,package-search,dependency-analysis,ai-assistant,claude,llm-tools,package-management,version-tracking,security-scanning
Platform: unix
Platform: linux
Platform: osx
Platform: win32
Classifier: Development Status :: 5 - Production/Stable
Classifier: Intended Audience :: Developers
Classifier: Intended Audience :: Information Technology
Classifier: Intended Audience :: System Administrators
Classifier: License :: OSI Approved :: MIT License
Classifier: License :: Other/Proprietary License
Classifier: Operating System :: OS Independent
Classifier: Programming Language :: Python :: 3
Classifier: Programming Language :: Python :: 3.10
Classifier: Programming Language :: Python :: 3.11
Classifier: Programming Language :: Python :: 3.12
Classifier: Programming Language :: Python :: 3.13
Classifier: Topic :: Software Development :: Libraries :: Python Modules
Classifier: Topic :: System :: Software Distribution
Classifier: Topic :: Internet :: WWW/HTTP
Classifier: Topic :: Software Development :: Build Tools
Classifier: Topic :: Software Development :: Quality Assurance
Classifier: Topic :: Security
Classifier: Topic :: System :: Monitoring
Classifier: Framework :: AsyncIO
Classifier: Environment :: Console
Classifier: Natural Language :: English
Classifier: Typing :: Typed
Requires-Python: >=3.10
License-File: LICENSE
Requires-Dist: mcp>=1.9.4
Requires-Dist: aiohttp>=3.12.13
Requires-Dist: packaging>=23.0
Requires-Dist: typer>=0.9.0
Requires-Dist: rich>=13.0.0
Requires-Dist: pydantic<3.0.0,>=2.11.7
Requires-Dist: defusedxml>=0.7.1
Requires-Dist: tomli>=2.0.0; python_version < "3.11"
Requires-Dist: typing_extensions>=4.3.0; python_version < "3.11"
Provides-Extra: all
Requires-Dist: beautifulsoup4>=4.12.0; extra == "all"
Requires-Dist: plotly>=5.13.0; extra == "all"
Requires-Dist: kaleido>=0.2.1; extra == "all"
Provides-Extra: dev
Requires-Dist: pytest>=7.0.0; extra == "dev"
Requires-Dist: pytest-cov>=4.0.0; extra == "dev"
Requires-Dist: pytest-asyncio>=0.21.0; extra == "dev"
Requires-Dist: black>=23.0.0; extra == "dev"
Requires-Dist: isort>=5.12.0; extra == "dev"
Requires-Dist: mypy>=1.0.0; extra == "dev"
Requires-Dist: pylint>=2.17.0; extra == "dev"
Provides-Extra: viz
Requires-Dist: plotly>=5.13.0; extra == "viz"
Requires-Dist: kaleido>=0.2.1; extra == "viz"
Provides-Extra: search
Requires-Dist: beautifulsoup4>=4.12.0; extra == "search"
Provides-Extra: docs
Requires-Dist: sphinx>=6.0.0; extra == "docs"
Requires-Dist: sphinx-rtd-theme>=1.2.0; extra == "docs"
Requires-Dist: myst-parser>=1.0.0; extra == "docs"
Dynamic: license-file
